__init__.py
autoservice/main.py
autoservice/services/__init__.py
autoservice/services/base.py
autoservice/services/npm.py
autoservice/services/python.py
autoservice/services/shell.py
autoservice-0.1.3.dist-info/METADATA
autoservice-0.1.3.dist-info/WHEEL
autoservice-0.1.3.dist-info/entry_points.txt
autoservice-0.1.3.dist-info/top_level.txt
autoservice-0.1.3.dist-info/RECORD
