Metadata-Version: 2.4
Name: autoservice
Version: 0.1.3
Summary: 一个简单高效的 systemd 服务管理工具，支持自动创建配置文件并智能适配不同类型的服务。
Author-email: Yaowen Liu <liuyaowen_smile@126.com>
License-Expression: MIT
Project-URL: Repository, https://github.com/OpenAISpace/autoservice
Project-URL: Documentation, https://github.com/OpenAISpace/autoservice#readme
Keywords: systemd,service,linux,daemon,process-manager
Classifier: Development Status :: 4 - Beta
Classifier: Environment :: Console
Classifier: Intended Audience :: System Administrators
Classifier: Operating System :: POSIX :: Linux
Classifier: Programming Language :: Python :: 3
Classifier: Topic :: System :: Systems Administration
Requires-Python: >=3.8
Requires-Dist: click>=8.0.0
